kronus/__init__.py
kronus/excepcions.py
kronus/kronus.py
kronus/kronus_uteis.py
kronus-2.3.dist-info/LICENSE
kronus-2.3.dist-info/METADATA
kronus-2.3.dist-info/WHEEL
kronus-2.3.dist-info/top_level.txt
kronus-2.3.dist-info/RECORD
